codeant_cli/__init__.py
codeant_cli/__main__.py
codeant_cli/config.py
codeant_cli/git_diff.py
codeant_cli/llm.py
codeant_cli/prompts.py
codeant_cli/report.py
codeant_cli/review.py
codeant_cli-1.0.3.dist-info/METADATA
codeant_cli-1.0.3.dist-info/WHEEL
codeant_cli-1.0.3.dist-info/entry_points.txt
codeant_cli-1.0.3.dist-info/top_level.txt
codeant_cli-1.0.3.dist-info/RECORD
