Metadata-Version: 2.4
Name: codeant-cli
Version: 1.0.3
Summary: AI-assisted code review CLI for PR workflows
Author-email: Satyam Gijare <satyam.gijare@gmail.com>
License: MIT
Requires-Python: >=3.9
Requires-Dist: typer>=0.12
Requires-Dist: rich>=13.7
Requires-Dist: pyyaml>=6.0
Requires-Dist: pydantic>=2.7
Requires-Dist: requests>=2.32
Requires-Dist: openai>=1.43.0
Requires-Dist: tiktoken>=0.7.0
